<?xml version="1.0"?>
<opencv_storage>
<keypoints type_id="opencv-matrix">
  <rows>25</rows>
  <cols>7</cols>
  <dt>d</dt>
  <data>
    1.2005621910095215e+01 3.3046451568603516e+01 3.1823964118957520e+00
    3.3841992187500000e+02 8.2697220146656036e-02 7930879. -1.
    1.4584840774536133e+01 3.3267238616943359e+01 6.5544390678405762e+00
    3.0870483398437500e+01 6.2445200979709625e-02 10093312. -1.
    1.4584840774536133e+01 3.3267238616943359e+01 6.5544390678405762e+00
    3.2935614013671875e+02 6.2445200979709625e-02 10093312. -1.
    1.4893548965454102e+01 3.0414833068847656e+01 1.8401263952255249e+00
    1.3450500488281250e+01 5.6993667036294937e-02 1769983. -1.
    2.1534608840942383e+01 2.7762569427490234e+01 2.4135081768035889e+00
    2.0019378662109375e+02 7.0146575570106506e-02 4653823. -1.
    2.4029088973999023e+01 3.1652412414550781e+01 1.8784370422363281e+00
    2.8337402343750000e+00 3.2779034227132797e-02 3277311. -1.
    2.5977128982543945e+01 2.2286764144897461e+01 2.5151016712188721e+00
    2.3167398071289063e+02 6.0731869190931320e-02 7668479. -1.
    2.8019153594970703e+01 4.5070655822753906e+01 2.5329346656799316e+00
    1.1987281799316406e+02 9.3277715146541595e-02 8127231. -1.
    3.0038562774658203e+01 2.9533458709716797e+01 1.0961810111999512e+01
    4.4268829345703125e+01 3.7926364690065384e-02 13828609. -1.
    3.0437486648559570e+01 1.4537362098693848e+01 1.8178589344024658e+00
    7.1965423583984375e+01 5.5926777422428131e-02 852479. -1.
    3.1276554107666016e+01 4.2327598571777344e+01 2.6340034008026123e+00
    1.9266801452636719e+02 5.4322276264429092e-02 11010815. -1.
    3.1387176513671875e+01 3.0594867706298828e+01 1.1862849235534668e+01
    4.6817749023437500e+01 3.8633473217487335e-02 2884353. -1.
    3.3063659667968750e+01 1.1856596946716309e+01 3.0330393314361572e+00
    1.0980360412597656e+02 7.9335637390613556e-02 4457471. -1.
    3.3074871063232422e+01 5.0719173431396484e+01 4.9835591316223145e+00
    2.5260494995117188e+02 5.8361392468214035e-02 6947328. -1.
    3.3074871063232422e+01 5.0719173431396484e+01 4.9835591316223145e+00
    2.8902386474609375e+02 5.8361392468214035e-02 6947328. -1.
    3.3492038726806641e+01 1.4391414642333984e+01 6.1110396385192871e+00
    6.0008239746093750e+01 6.4798243343830109e-02 5047040. -1.
    3.3492038726806641e+01 1.4391414642333984e+01 6.1110396385192871e+00
    1.1792779541015625e+02 6.4798243343830109e-02 5047040. -1.
    3.4016365051269531e+01 4.6209297180175781e+01 2.7264268398284912e+00
    8.9246490478515625e+01 7.2819858789443970e-02 13501183. -1.
    3.4022853851318359e+01 4.0110473632812500e+01 1.9748529195785522e+00
    1.7131803894042969e+02 4.5690149068832397e-02 6881791. -1.
    3.4890022277832031e+01 1.9540393829345703e+01 1.8482626676559448e+00
    2.8069256591796875e+02 4.3777775019407272e-02 2097663. -1.
    3.6683666229248047e+01 1.4481595039367676e+01 1.8371227979660034e+00
    1.0782319641113281e+02 5.4997216910123825e-02 1638911. -1.
    3.7694274902343750e+01 2.9123497009277344e+01 1.9275358915328979e+00
    2.6081542968750000e+00 3.6729048937559128e-02 5112319. -1.
    3.7694274902343750e+01 2.9123497009277344e+01 1.9275358915328979e+00
    2.2128083801269531e+02 3.6729048937559128e-02 5112319. -1.
    3.8514842987060547e+01 3.7082801818847656e+01 2.5072290897369385e+00
    2.3223754882812500e+01 2.6900915428996086e-02 7406335. -1.
    4.6700878143310547e+01 3.6928649902343750e+01 1.8665634393692017e+00
    1.7975952148437500e+01 6.9828733801841736e-02 2818559. -1.</data></keypoints>
<descriptors type_id="opencv-matrix">
  <rows>25</rows>
  <cols>128</cols>
  <dt>f</dt>
  <data>
    0. 0. 0. 0. 0. 0. 0. 2. 2. 0. 0. 0. 0. 0. 10. 48. 5. 0. 0. 0. 0. 0.
    20. 125. 2. 0. 2. 4. 0. 0. 20. 125. 20. 0. 0. 0. 0. 0. 0. 11. 119.
    5. 1. 0. 0. 4. 52. 125. 15. 2. 2. 3. 4. 43. 125. 125. 6. 0. 8. 119.
    34. 1. 15. 125. 43. 3. 0. 0. 0. 0. 0. 2. 125. 105. 17. 1. 0. 2. 4.
    29. 62. 77. 36. 20. 36. 20. 24. 21. 4. 2. 1. 125. 125. 8. 7. 13. 25.
    2. 0. 0. 0. 0. 0. 0. 125. 46. 3. 0. 0. 0. 0. 0. 125. 36. 4. 3. 54.
    2. 0. 4. 6. 1. 0. 8. 125. 45. 2. 1. 37. 0. 0. 0. 0. 0. 0. 10. 132.
    1. 0. 6. 25. 1. 0. 83. 28. 4. 27. 87. 130. 7. 1. 21. 14. 25. 48. 19.
    6. 2. 1. 10. 66. 6. 0. 0. 0. 0. 0. 1. 132. 31. 3. 1. 25. 22. 3. 29.
    29. 8. 6. 6. 119. 132. 41. 13. 15. 1. 0. 0. 4. 36. 74. 44. 24. 17.
    0. 0. 0. 0. 0. 0. 111. 132. 61. 0. 1. 5. 1. 6. 9. 132. 132. 2. 6.
    77. 35. 2. 0. 23. 97. 6. 0. 46. 101. 11. 0. 2. 0. 0. 0. 0. 0. 0. 0.
    41. 18. 0. 0. 0. 0. 0. 0. 95. 97. 0. 0. 0. 0. 0. 0. 27. 132. 11. 0.
    0. 0. 0. 0. 0. 0. 0. 0. 0. 0. 2. 0. 0. 0. 0. 0. 0. 16. 41. 0. 0. 0.
    0. 0. 0. 91. 97. 0. 0. 1. 1. 0. 2. 134. 30. 25. 0. 0. 0. 0. 0. 0.
    18. 106. 4. 0. 3. 4. 1. 66. 134. 7. 1. 27. 87. 28. 4. 131. 134. 3.
    35. 114. 71. 1. 1. 80. 24. 69. 2. 0. 0. 0. 0. 0. 5. 134. 33. 1. 10.
    27. 2. 5. 33. 34. 8. 11. 109. 134. 32. 12. 8. 12. 16. 32. 45. 18.
    14. 22. 9. 36. 10. 0. 0. 0. 0. 0. 0. 134. 99. 1. 0. 14. 3. 0. 0. 31.
    31. 1. 1. 107. 83. 10. 1. 1. 0. 0. 0. 14. 35. 56. 30. 73. 0. 0. 0.
    0. 0. 0. 13. 68. 0. 0. 3. 10. 0. 0. 12. 134. 0. 0. 5. 31. 0. 0. 36.
    12. 0. 1. 53. 134. 1. 0. 3. 82. 0. 0. 0. 0. 1. 9. 59. 74. 1. 0. 1.
    7. 24. 39. 29. 134. 5. 0. 0. 46. 6. 5. 15. 14. 1. 0. 2. 134. 31. 0.
    1. 103. 11. 0. 0. 0. 2. 25. 134. 19. 3. 0. 1. 8. 83. 116. 53. 122.
    15. 1. 2. 29. 27. 25. 27. 15. 5. 0. 0. 134. 85. 1. 0. 93. 134. 2. 0.
    0. 0. 1. 13. 14. 63. 23. 50. 25. 16. 7. 4. 31. 64. 18. 48. 22. 8. 2.
    1. 21. 30. 0. 0. 64. 81. 0. 0. 16. 26. 9. 6. 7. 2. 0. 2. 64. 108.
    19. 13. 21. 6. 0. 0. 135. 120. 2. 5. 37. 9. 1. 1. 5. 12. 55. 38. 65.
    7. 1. 2. 36. 6. 1. 4. 12. 4. 1. 10. 90. 27. 1. 11. 66. 17. 2. 8.
    135. 68. 0. 2. 56. 4. 1. 15. 16. 3. 5. 12. 135. 10. 0. 0. 10. 34. 5.
    3. 5. 3. 1. 1. 67. 19. 2. 3. 16. 20. 23. 76. 135. 3. 0. 16. 59. 1.
    5. 135. 11. 0. 0. 42. 135. 1. 0. 4. 3. 16. 8. 4. 14. 4. 1. 5. 135.
    31. 5. 1. 1. 0. 1. 88. 115. 1. 0. 66. 65. 0. 0. 79. 0. 0. 0. 62. 94.
    0. 0. 1. 11. 1. 9. 162. 162. 0. 0. 11. 29. 57. 42. 96. 33. 2. 1. 20.
    14. 24. 2. 1. 28. 38. 1. 6. 8. 1. 0. 0. 20. 25. 2. 7. 14. 1. 0. 96.
    162. 2. 0. 5. 123. 11. 1. 12. 49. 4. 7. 77. 19. 5. 2. 35. 42. 11.
    10. 23. 4. 5. 7. 19. 19. 7. 2. 5. 9. 1. 0. 10. 162. 56. 6. 9. 125.
    11. 2. 8. 34. 17. 10. 46. 18. 5. 5. 59. 73. 10. 3. 6. 8. 4. 6. 12.
    6. 1. 5. 20. 3. 1. 0. 0. 162. 161. 12. 3. 9. 0. 0. 1. 16. 49. 45.
    35. 1. 0. 1. 7. 58. 43. 7. 5. 34. 18. 8. 9. 12. 4. 3. 13. 9. 17. 5.
    1. 11. 20. 3. 1. 115. 59. 3. 0. 7. 18. 15. 23. 135. 62. 0. 0. 65.
    41. 0. 5. 1. 1. 0. 0. 112. 54. 0. 0. 2. 14. 25. 3. 4. 5. 2. 0. 68.
    73. 49. 5. 3. 4. 4. 7. 135. 129. 3. 2. 68. 7. 0. 6. 10. 4. 0. 3.
    135. 17. 0. 0. 3. 3. 2. 1. 4. 15. 9. 3. 85. 10. 7. 3. 11. 28. 5. 42.
    135. 16. 1. 15. 63. 1. 1. 90. 12. 0. 0. 33. 135. 1. 0. 2. 2. 1. 0.
    0. 1. 21. 28. 7. 57. 0. 0. 0. 3. 14. 15. 135. 114. 0. 0. 48. 68. 2.
    1. 115. 1. 0. 0. 58. 88. 4. 1. 0. 0. 4. 49. 52. 1. 1. 31. 21. 101.
    102. 19. 12. 1. 1. 38. 43. 106. 73. 1. 8. 63. 29. 2. 5. 0. 0. 2. 41.
    121. 34. 1. 0. 7. 13. 19. 9. 5. 5. 68. 89. 41. 44. 24. 48. 55. 13.
    57. 39. 121. 121. 14. 9. 68. 16. 1. 13. 10. 3. 0. 1. 121. 48. 0. 0.
    32. 52. 56. 39. 4. 1. 4. 9. 58. 35. 8. 15. 50. 40. 32. 42. 121. 11.
    2. 9. 61. 9. 18. 106. 14. 0. 0. 20. 121. 9. 0. 3. 44. 7. 3. 7. 1. 1.
    6. 46. 92. 13. 2. 0. 0. 2. 9. 54. 91. 1. 0. 33. 57. 0. 4. 60. 2. 0.
    0. 52. 114. 0. 0. 1. 13. 0. 0. 0. 0. 0. 4. 30. 13. 0. 3. 4. 0. 1.
    115. 100. 0. 3. 7. 3. 1. 60. 115. 11. 0. 0. 0. 0. 9. 58. 24. 0. 115.
    3. 0. 0. 0. 0. 1. 49. 104. 8. 37. 72. 32. 16. 38. 78. 65. 55. 54.
    29. 17. 44. 50. 15. 22. 7. 0. 6. 115. 108. 9. 2. 115. 48. 1. 0. 0.
    0. 0. 4. 108. 79. 43. 10. 28. 71. 47. 10. 51. 10. 55. 48. 16. 25.
    75. 58. 18. 1. 9. 112. 115. 6. 1. 7. 13. 30. 4. 0. 0. 0. 0. 0. 12.
    100. 115. 1. 0. 3. 3. 0. 0. 12. 115. 61. 1. 2. 7. 2. 0. 0. 23. 59.
    10. 0. 0. 0. 98. 14. 1. 0. 0. 0. 0. 128. 28. 9. 12. 12. 9. 25. 16.
    120. 10. 3. 6. 10. 15. 62. 31. 43. 15. 0. 0. 66. 40. 0. 5. 47. 123.
    124. 12. 0. 0. 0. 0. 9. 30. 82. 128. 44. 2. 1. 0. 5. 94. 44. 43. 27.
    17. 2. 2. 9. 14. 2. 0. 108. 128. 0. 0. 4. 94. 29. 4. 0. 0. 0. 0. 6.
    79. 27. 39. 12. 5. 1. 0. 4. 128. 12. 7. 7. 44. 2. 0. 17. 12. 1. 1.
    55. 128. 5. 0. 2. 79. 7. 0. 0. 0. 0. 0. 2. 77. 5. 0. 0. 8. 5. 0. 2.
    128. 18. 0. 0. 37. 6. 0. 2. 10. 2. 0. 2. 128. 31. 0. 0. 4. 2. 90.
    90. 3. 1. 29. 65. 6. 40. 117. 39. 3. 10. 47. 6. 3. 52. 117. 39. 8.
    23. 70. 1. 5. 95. 57. 0. 0. 59. 67. 1. 5. 3. 47. 117. 104. 34. 1. 2.
    117. 57. 75. 30. 31. 19. 6. 25. 36. 38. 69. 39. 27. 83. 59. 24. 46.
    117. 51. 3. 0. 5. 19. 27. 4. 1. 0. 49. 117. 23. 1. 2. 117. 55. 3. 7.
    41. 11. 4. 28. 37. 25. 43. 78. 66. 26. 11. 7. 13. 78. 81. 16. 10. 5.
    4. 4. 9. 1. 1. 43. 69. 4. 1. 4. 58. 9. 7. 7. 6. 3. 4. 40. 17. 7. 16.
    40. 65. 22. 0. 4. 18. 20. 4. 8. 21. 12. 2. 3. 7. 0. 0. 0. 0. 0. 5.
    24. 5. 0. 0. 1. 0. 2. 119. 85. 0. 0. 1. 0. 1. 50. 119. 9. 0. 0. 0.
    0. 5. 25. 12. 0. 119. 2. 0. 0. 0. 0. 2. 58. 96. 10. 28. 45. 14. 11.
    66. 106. 47. 39. 28. 17. 32. 83. 85. 13. 5. 1. 0. 4. 119. 101. 9. 0.
    119. 52. 1. 0. 0. 0. 0. 4. 114. 85. 45. 15. 15. 45. 43. 16. 46. 13.
    58. 77. 37. 17. 43. 50. 6. 1. 5. 89. 119. 11. 0. 1. 17. 33. 5. 0. 0.
    0. 0. 0. 13. 104. 119. 3. 0. 1. 3. 0. 0. 8. 119. 75. 2. 1. 3. 1. 0.
    0. 16. 40. 10. 0. 0. 0. 31. 0. 0. 0. 0. 0. 0. 2. 126. 0. 0. 0. 0. 0.
    2. 49. 126. 1. 0. 2. 62. 11. 3. 40. 4. 0. 0. 12. 126. 33. 2. 1. 52.
    2. 0. 0. 0. 0. 0. 3. 126. 29. 5. 2. 0. 0. 11. 112. 49. 15. 33. 16.
    43. 19. 24. 89. 1. 5. 6. 11. 126. 102. 0. 1. 25. 14. 0. 0. 0. 0. 0.
    0. 121. 126. 52. 4. 0. 0. 0. 4. 16. 126. 126. 31. 4. 3. 1. 2. 9.
    102. 14. 1. 41. 126. 2. 0. 0. 2. 0. 0. 0. 0. 0. 0. 4. 59. 9. 0. 0.
    0. 0. 0. 11. 126. 17. 0. 0. 0. 0. 0. 5. 126. 16. 0. 0. 10. 1. 0. 1.
    0. 0. 0. 0. 0. 0. 3. 16. 0. 0. 0. 0. 0. 1. 93. 9. 1. 4. 3. 0. 0. 41.
    136. 0. 1. 29. 21. 0. 0. 94. 94. 24. 0. 0. 0. 0. 0. 0. 13. 136. 3.
    0. 3. 2. 0. 1. 136. 24. 2. 20. 98. 34. 1. 7. 136. 0. 1. 80. 116. 19.
    4. 3. 10. 50. 4. 0. 0. 0. 0. 0. 2. 136. 41. 1. 6. 13. 6. 1. 28. 53.
    11. 13. 76. 110. 98. 3. 12. 0. 12. 31. 26. 29. 47. 1. 0. 21. 6. 0.
    0. 0. 0. 0. 0. 136. 105. 0. 0. 1. 4. 1. 1. 61. 59. 2. 1. 50. 110. 2.
    2. 1. 2. 3. 1. 39. 116. 1. 0. 33. 0. 0. 0. 0. 0. 0. 8. 139. 0. 1. 3.
    3. 0. 0. 88. 53. 0. 2. 101. 59. 3. 0. 45. 0. 0. 3. 80. 53. 23. 6. 0.
    59. 4. 0. 0. 0. 0. 0. 1. 139. 30. 0. 2. 15. 4. 1. 31. 49. 9. 6. 43.
    139. 46. 10. 10. 0. 0. 19. 31. 24. 38. 36. 0. 23. 15. 0. 0. 0. 0. 0.
    0. 123. 139. 1. 1. 4. 2. 0. 3. 30. 139. 7. 3. 44. 83. 57. 3. 1. 11.
    7. 3. 5. 94. 137. 0. 1. 2. 0. 0. 0. 0. 0. 0. 7. 89. 1. 0. 0. 0. 0.
    0. 7. 139. 51. 0. 0. 3. 3. 0. 0. 97. 118. 1. 2. 25. 11. 0. 0. 0. 0.
    0. 0. 0. 0. 2. 0. 0. 0. 0. 0. 0. 14. 45. 0. 0. 0. 0. 0. 0. 88. 118.
    0. 0. 3. 1. 0. 6. 136. 43. 21. 0. 0. 0. 0. 0. 0. 15. 112. 5. 1. 3.
    1. 0. 44. 136. 13. 2. 13. 84. 13. 4. 125. 136. 1. 10. 100. 74. 1. 2.
    68. 28. 60. 1. 0. 0. 0. 0. 0. 6. 136. 30. 4. 16. 13. 2. 2. 35. 40.
    14. 23. 136. 105. 15. 6. 12. 13. 20. 56. 64. 6. 2. 0. 2. 37. 8. 0.
    0. 0. 0. 0. 0. 136. 70. 0. 1. 12. 7. 0. 1. 38. 22. 1. 11. 113. 116.
    9. 1. 21. 5. 2. 2. 10. 37. 37. 20. 36. 0. 0. 0. 0. 0. 0. 8. 137. 0.
    0. 3. 12. 2. 0. 87. 35. 0. 8. 72. 120. 6. 0. 28. 2. 23. 52. 28. 18.
    0. 0. 0. 63. 5. 0. 0. 0. 0. 0. 1. 137. 42. 5. 1. 15. 11. 2. 35. 40.
    13. 9. 16. 137. 117. 9. 12. 3. 12. 11. 19. 35. 40. 46. 9. 22. 16. 0.
    0. 0. 0. 0. 0. 101. 137. 49. 1. 2. 1. 0. 2. 9. 137. 113. 6. 36. 70.
    22. 1. 1. 33. 60. 0. 5. 61. 137. 13. 0. 2. 0. 0. 0. 0. 0. 0. 0. 45.
    12. 0. 0. 0. 0. 0. 0. 120. 79. 0. 0. 0. 0. 0. 0. 53. 137. 0. 0. 0.
    3. 0. 4. 72. 43. 2. 1. 3. 3. 2. 23. 98. 56. 7. 0. 2. 2. 4. 26. 109.
    16. 2. 71. 69. 0. 0. 1. 1. 0. 0. 99. 90. 0. 0. 2. 39. 44. 5. 6. 22.
    33. 3. 23. 60. 115. 10. 1. 16. 32. 7. 115. 112. 21. 3. 36. 22. 4.
    18. 14. 3. 1. 2. 101. 115. 3. 1. 11. 27. 23. 6. 3. 27. 80. 16. 32.
    17. 21. 30. 8. 59. 106. 34. 115. 15. 5. 20. 29. 6. 20. 104. 13. 0.
    27. 83. 77. 35. 1. 4. 48. 26. 19. 9. 8. 5. 6. 30. 50. 16. 17. 47.
    31. 17. 23. 71. 115. 10. 4. 55. 52. 0. 2. 82. 2. 0. 6. 80. 91. 0. 0.
    0. 0. 0. 10. 72. 57. 24. 2. 0. 8. 0. 6. 79. 118. 21. 3. 14. 118. 19.
    10. 12. 24. 4. 2. 118. 40. 20. 33. 32. 83. 59. 9. 37. 0. 0. 46. 118.
    35. 0. 0. 0. 56. 5. 6. 78. 118. 9. 7. 20. 118. 35. 5. 18. 9. 4. 5.
    115. 18. 19. 55. 58. 30. 82. 20. 19. 10. 7. 24. 74. 32. 1. 1. 16.
    28. 5. 4. 7. 22. 18. 46. 98. 118. 21. 3. 24. 44. 1. 16. 103. 7. 33.
    63. 85. 118. 4. 0. 1. 44. 3. 1. 17. 9. 0. 0. 40. 24. 11. 15. 5. 0.
    0. 2. 52. 15. 30. 59. 32. 28. 0. 1. 12. 3. 3. 13. 35. 105. 13. 4. 4.
    4. 5. 1. 0. 0. 16. 27. 4. 148. 110. 0. 0. 0. 11. 11. 7. 148. 104. 0.
    0. 30. 50. 1. 0. 10. 3. 1. 1. 24. 71. 35. 61. 11. 3. 1. 0. 0. 4. 19.
    24. 133. 16. 0. 0. 0. 7. 27. 23. 148. 60. 0. 4. 18. 7. 1. 9. 23. 24.
    34. 43. 60. 14. 5. 7. 7. 14. 15. 1. 1. 3. 30. 29. 76. 19. 30. 1. 0.
    4. 48. 30. 148. 13. 1. 3. 36. 1. 2. 39. 22. 6. 16. 43. 148. 1. 0. 3.
    1. 8. 22. 5. 9. 37. 2. 0. 81. 25. 45. 3. 1. 9. 5. 38. 148. 13. 2.
    11. 39. 0. 0. 63. 12. 0. 0. 43. 148. 0. 0. 3. 87. 0. 0. 0. 0. 0. 0.
    10. 95. 2. 0. 5. 7. 0. 0. 6. 132. 3. 0. 4. 42. 2. 0. 16. 8. 0. 0.
    24. 132. 25. 5. 1. 111. 0. 0. 0. 0. 0. 4. 27. 94. 3. 0. 1. 5. 13.
    44. 31. 132. 20. 0. 0. 42. 5. 8. 14. 11. 2. 2. 8. 132. 30. 2. 0.
    132. 2. 0. 0. 0. 0. 6. 57. 80. 0. 0. 1. 3. 36. 128. 84. 92. 13. 3.
    3. 21. 23. 45. 44. 13. 6. 1. 2. 132. 75. 0. 1. 132. 31. 1. 0. 0. 0.
    0. 17. 101. 36. 24. 37. 14. 9. 9. 18. 9. 51. 32. 72. 21. 8. 5. 2.
    15. 53. 5. 0. 66. 70. 0. 0. 57. 57. 11. 6. 4. 0. 0. 1. 43. 33. 12.
    35. 22. 3. 14. 49. 2. 0. 0. 9. 58. 24. 54. 105. 31. 35. 11. 5. 53.
    13. 6. 29. 70. 56. 5. 6. 20. 3. 0. 0. 135. 46. 2. 9. 3. 1. 6. 95.
    25. 2. 3. 122. 130. 16. 21. 73. 10. 9. 41. 82. 55. 5. 0. 6. 56. 28.
    6. 7. 30. 21. 33. 38. 135. 45. 19. 74. 10. 0. 6. 44. 20. 11. 32.
    135. 46. 0. 1. 4. 13. 3. 19. 103. 18. 3. 15. 61. 8. 0. 0. 0. 1. 8.
    65. 96. 23. 4. 4. 40. 78. 10. 21. 44. 40. 5. 9. 70. 88. 14. 2. 44.
    34. 1. 2. 2. 2. 3. 48. 135. 48. 95. 10. 1. 35. 24. 0. 0. 44. 65. 5.
    32. 50. 26. 3. 5. 3. 13. 19. 77. 85. 60. 11. 3. 15. 53. 12. 4. 8. 6.
    8. 5. 63. 28. 5. 21. 90. 38. 6. 18. 137. 28. 0. 0. 20. 82. 19. 58.
    13. 1. 0. 2. 68. 137. 46. 10. 7. 17. 2. 0. 3. 91. 43. 4. 98. 12. 3.
    25. 69. 7. 3. 29. 137. 74. 4. 6. 15. 12. 2. 29. 31. 29. 8. 42. 137.
    90. 7. 3. 15. 3. 1. 7. 23. 102. 48. 10. 33. 1. 0. 5. 35. 15. 26. 83.
    49. 94. 11. 6. 16. 11. 8. 19. 14. 66. 22. 73. 83. 1. 0. 0. 73. 57.
    3. 14. 25. 24. 9. 12. 61. 64. 6. 17. 13. 2. 2. 11. 20. 8. 5. 74. 75.
    5. 1. 12. 75. 1. 1. 8. 6. 8. 15. 126. 75. 49. 0. 0. 4. 59. 24. 30.
    26. 6. 1. 3. 20. 11. 14. 80. 58. 2. 1. 10. 92. 37. 4. 14. 126. 28.
    2. 2. 4. 9. 15. 93. 78. 16. 5. 27. 53. 96. 30. 37. 25. 14. 0. 16.
    65. 22. 23. 43. 50. 13. 8. 38. 89. 13. 3. 23. 126. 39. 2. 2. 3. 2.
    1. 72. 82. 18. 5. 32. 56. 27. 16. 45. 55. 22. 2. 7. 63. 61. 12. 36.
    73. 39. 5. 14. 104. 75. 1. 5. 126. 80. 1. 0. 1. 1. 1. 41. 80. 10. 0.
    6. 5. 11. 30. 115. 34. 0. 0. 2. 6. 4. 4. 49. 69. 49. 1. 3. 17. 10.
    3. 5. 141. 95. 0. 0. 16. 9. 0. 0. 9. 3. 1. 52. 86. 12. 3. 2. 23. 0.
    0. 0. 3. 23. 29. 91. 46. 18. 1. 0. 40. 101. 18. 8. 141. 62. 1. 0.
    22. 10. 1. 8. 36. 3. 0. 15. 141. 19. 0. 0. 84. 19. 5. 7. 5. 13. 13.
    45. 29. 3. 4. 43. 78. 94. 11. 16. 141. 4. 0. 7. 29. 15. 2. 60. 39.
    0. 0. 31. 141. 3. 0. 5. 56. 26. 5. 9. 11. 2. 0. 10. 45. 4. 4. 57.
    66. 8. 2. 22. 141. 1. 1. 19. 30. 0. 0. 78. 12. 0. 0. 63. 141. 0. 0.
    4.</data></descriptors>
</opencv_storage>
